[
  {
    "author": [
      {
        "family": "Bentham",
        "given": "G."
      }
    ],
    "title": "Synopsis of the Buchnereae, a tribe of the Scrophulariaceae. Companion to the botanical magazine",
    "volume": "1",
    "type": "article-journal",
    "container-title": "London",
    "issued": "1836",
    "page": "356–384"
  },
  {
    "author": [
      {
        "family": "Botanga",
        "given": "C.J."
      },
      {
        "family": "Timko",
        "given": "M.P."
      }
    ],
    "title": "Genetic structure and analysis of host and nonhost interactions of Striga gesnerioides (witchweed) from Central Florida",
    "volume": "95",
    "type": "article-journal",
    "container-title": "Phytopathology",
    "issued": "2005",
    "page": "1166–1173",
    "URL": "http://dx.doi.org/10.1094/PHYTO-95-1166",
    "DOI": "10.1094/PHYTO-95-1166"
  },
  {
    "author": [
      {
        "family": "Fischer",
        "given": "E."
      },
      {
        "family": "Lobin",
        "given": "W."
      },
      {
        "family": "Mutke",
        "given": "J."
      }
    ],
    "title": "Striga barthlottii (Orobanchaceae), a new parasitic species from Morocco",
    "volume": "41",
    "type": "article-journal",
    "container-title": "Willdenowia",
    "issued": "2011",
    "page": "51–56",
    "URL": "http://dx.doi.org/10.3372/wi.41.41105",
    "DOI": "10.3372/wi.41.41105"
  },
  {
    "author": [
      {
        "family": "Gamble",
        "given": "J.S."
      },
      {
        "family": "Fischer",
        "given": "C.E.C."
      }
    ],
    "title": "Flora of the Presidency of Madras",
    "publisher": "Newman and Adlard",
    "edition": "reprint",
    "volume": "II",
    "type": "book",
    "issued": "1923",
    "page": "862",
    "publisher-place": "London"
  },
  {
    "author": [
      {
        "family": "Hooker",
        "given": "J.D."
      }
    ],
    "title": "The Flora of British India",
    "volume": "I–VII",
    "publisher": "Reeve & Co",
    "type": "book",
    "issued": "1884",
    "page": "5567",
    "publisher-place": "London"
  },
  {
    "title": "IUCN standards and petitions subcommittee",
    "container-title": "Version 8.0. Prepared by the Standards and Petitions Subcommittee",
    "type": "chapter",
    "issued": "2010"
  },
  {
    "author": [
      {
        "family": "Jayanthi",
        "given": "P."
      },
      {
        "family": "Prabhu Kumar",
        "given": "K.M."
      },
      {
        "family": "Rajendran",
        "given": "A."
      },
      {
        "family": "Thomas",
        "given": "B."
      },
      {
        "family": "Sabu",
        "given": "M."
      },
      {
        "family": "Pradeep",
        "given": "A.K."
      }
    ],
    "title": "Striga indica (Orobanchaceae)–A new parasitic species from Southern Western Ghats of India",
    "volume": "123",
    "type": "article-journal",
    "container-title": "Feddes Reperorium",
    "issued": "2014",
    "page": "283–290",
    "URL": "http://dx.doi.org/10.1002/fedr.201200025",
    "DOI": "10.1002/fedr.201200025"
  },
  {
    "author": [
      {
        "family": "Jeeva",
        "given": "S."
      },
      {
        "family": "Shynin Brintha",
        "given": "T.S."
      },
      {
        "family": "Rasingam",
        "given": "L."
      }
    ],
    "title": "Striga scottiana (Scrophulariaceae) – a new species from southern Western Ghats of Tamilnadu, India",
    "volume": "6",
    "type": "article-journal",
    "container-title": "Journal of Basic and Applied Biology",
    "issue": "3&4",
    "issued": "2012",
    "page": "79–82"
  },
  {
    "author": [
      {
        "family": "Mohamed",
        "given": "K.I."
      },
      {
        "family": "Musselman",
        "given": "L.J."
      },
      {
        "family": "Riches",
        "given": "C.R."
      }
    ],
    "title": "The genus Striga (Scrophulariaceae) in Africa",
    "volume": "88",
    "type": "article-journal",
    "container-title": "Annals of the Missouri Botanic Garden",
    "issued": "2001",
    "page": "60–103",
    "URL": "http://dx.doi.org/10.2307/2666132",
    "DOI": "10.2307/2666132"
  },
  {
    "author": [
      {
        "family": "Linnaeus",
        "given": "C."
      }
    ],
    "title": "Species Plantarum",
    "type": null,
    "issued": "1753",
    "page": "82",
    "publisher-place": "Salvius, Stockholm"
  },
  {
    "author": [
      {
        "family": "Loureiro",
        "given": "J.de"
      }
    ],
    "title": "Flora of cochinchinensis",
    "publisher": "Ulyssipone, Lisbon",
    "type": "book",
    "issued": "1790",
    "page": "744"
  },
  {
    "author": [
      {
        "family": "Matthew",
        "given": "K.M."
      }
    ],
    "title": "The Flora of the Tamilnadu Carnatic",
    "container-title": "Part 1. The Rapinat Herbarium, Tiruchirapalli",
    "type": "chapter",
    "issued": "1981",
    "page": "1103–1106"
  },
  {
    "author": [
      {
        "family": "Musselman",
        "given": "L.J."
      },
      {
        "family": "Hepper",
        "given": "F.N."
      }
    ],
    "title": "Studies in the Flora of Arabia XX: The genus Striga in Arabia",
    "volume": "45",
    "type": "article-journal",
    "container-title": "Royal Botanic Garden Edinburgh",
    "issued": "1988",
    "page": "43–50"
  },
  {
    "author": [
      {
        "family": "Musselman",
        "given": "L.J."
      },
      {
        "family": "Parker",
        "given": "C."
      }
    ],
    "title": "Studies on indigo witchweed, the American strain of Striga gesnerioides (Scrophulariaceae",
    "volume": "29",
    "type": "article-journal",
    "container-title": "Weed Science",
    "issued": "1981",
    "page": "594–596"
  },
  {
    "author": [
      {
        "family": "Olmstead",
        "given": "R.G."
      },
      {
        "family": "Depamphilis",
        "given": "C.W."
      },
      {
        "family": "Wolfe",
        "given": "A.D."
      },
      {
        "family": "Young",
        "given": "N.D."
      },
      {
        "family": "Elisens",
        "given": "W.J."
      },
      {
        "family": "Reeves",
        "given": "P.A."
      }
    ],
    "title": "Disintegration of the Scrophulariaceae",
    "volume": "88",
    "type": "article-journal",
    "container-title": "American Journal of Botany",
    "issued": "2001",
    "page": "348–361",
    "URL": "http://dx.doi.org/10.2307/2657024",
    "DOI": "10.2307/2657024"
  },
  {
    "author": [
      {
        "family": "Saldanha",
        "given": "C.J."
      }
    ],
    "title": "The genus Striga Lour",
    "volume": "5",
    "type": "article-journal",
    "container-title": "Bulletin of Botanical Survey of India",
    "issue": "1",
    "issued": "1963",
    "page": "67–70"
  },
  {
    "author": [
      {
        "family": "Sarvalingam",
        "given": "A."
      },
      {
        "family": "Rajendran",
        "given": "A."
      },
      {
        "family": "Sivalingam",
        "given": "R."
      }
    ],
    "title": "Documentary of Woody flora and its usage in Maruthamalai Hills of the Southern Western Ghats of Coimbatore district, India",
    "volume": "2",
    "type": "article-journal",
    "container-title": "Research in Plant Biology",
    "issue": "1",
    "issued": "2012",
    "page": "7–14"
  },
  {
    "author": [
      {
        "family": "Thalouarn",
        "given": "P."
      },
      {
        "family": "Arnaud",
        "given": "M.C."
      },
      {
        "family": "Theodet",
        "given": "C."
      },
      {
        "family": "Rey",
        "given": "L."
      }
    ],
    "title": "Cytological, biochemical and genetic aspects of carbon fixation in Striga hermonthica and Striga gesnerioides",
    "editor": [
      {
        "family": "Ransom",
        "given": "J.K."
      },
      {
        "family": "Musselman",
        "given": "L.J."
      },
      {
        "family": "Worsham",
        "given": "A.D."
      },
      {
        "family": "Parker",
        "given": "C."
      }
    ],
    "container-title": "Proceedings of the Fifth International Symposium on Parasitic Weeds. CIMMYT, Nairobi",
    "type": "paper-conference",
    "issued": "1991",
    "page": "51–57"
  },
  {
    "author": [
      {
        "family": "Vatke",
        "given": "W."
      }
    ],
    "title": "Hedyotis fugax Vatke",
    "volume": "25",
    "type": "article-journal",
    "container-title": "Oesterreichische botanische Zeitschrift",
    "issued": "1875",
    "page": "232"
  },
  {
    "author": [
      {
        "family": "Wettstein",
        "given": "RVon"
      }
    ],
    "title": "Scrophulariaceae",
    "editor": [
      {
        "family": "Engler",
        "given": "A."
      },
      {
        "family": "Prantl",
        "given": "K."
      }
    ],
    "container-title": "Die natürlichen Pflanzenfamilien IV",
    "type": "chapter",
    "issued": "1895",
    "page": "39–107",
    "publisher-place": "3b).Wilhelm Engelmann, Leipzig"
  },
  {
    "author": [
      {
        "family": "Willdenow",
        "given": "C.L."
      }
    ],
    "title": "Species Plantarum",
    "volume": "Berolini",
    "type": "article-journal",
    "container-title": "Editio Quarta",
    "issued": "1800",
    "page": "25"
  }
]
