[
  {
    "author": [
      {
        "family": "Anderson",
        "given": "T."
      }
    ],
    "title": "An enumeration of the species of the Indian Acanthaceae",
    "volume": "9",
    "type": "article-journal",
    "container-title": "Journal of the Linnaean Society Botany",
    "issued": "1867",
    "page": "425–526",
    "URL": "https://doi.org/10.1111/j.1095-8339.1867.tb01308.x",
    "DOI": "10.1111/j.1095-8339.1867.tb01308.x"
  },
  {
    "author": [
      {
        "family": "Bentham",
        "given": "G."
      }
    ],
    "title": "Flora Hongkongensis",
    "publisher": "Lovell Reeve",
    "type": "book",
    "issued": "1861",
    "page": "264",
    "publisher-place": "London"
  },
  {
    "author": [
      {
        "family": "Bentham",
        "given": "G."
      }
    ],
    "title": "Acanthaceae",
    "editor": [
      {
        "family": "Bentham",
        "given": "G."
      },
      {
        "family": "Hooker",
        "given": "J.D."
      }
    ],
    "container-title": "Genera Plantarum 2",
    "publisher": "Reeve & Co",
    "type": "chapter",
    "issued": "1876",
    "page": "1066–1122",
    "publisher-place": "London"
  },
  {
    "author": [
      {
        "family": "Clarke",
        "given": "C.B."
      }
    ],
    "title": "Acanthaceae",
    "editor": [
      {
        "family": "Hooker",
        "given": "J.D."
      }
    ],
    "publisher": "Reeve & Co",
    "type": "book",
    "issued": "1885",
    "page": "387–558",
    "publisher-place": "London"
  },
  {
    "author": [
      {
        "family": "Handel-Mazzetti",
        "given": "H."
      }
    ],
    "title": "Plantae novae sinenses, diagnosibus brevibus descriptae a Dre",
    "container-title": "Heinr. Handel-Mazzetti (37. Fortsetzung). Anzeiger der Akademie der Wissenschaften in Wien. Mathematische-naturwissenchaftliche Klasse",
    "volume": "62",
    "issue": "25",
    "type": "article-journal",
    "issued": "1925",
    "page": "235–236",
    "publisher-place": "Wien"
  },
  {
    "author": [
      {
        "family": "Handel-Mazzetti",
        "given": "H."
      }
    ],
    "title": "Symbolae Sinicae",
    "volume": "7",
    "publisher": "Julius Springer, Wien",
    "issue": "4",
    "type": "book",
    "issued": "1936",
    "page": "899"
  },
  {
    "author": [
      {
        "family": "Hu",
        "given": "C.C."
      }
    ],
    "title": "Justiciinae",
    "editor": [
      {
        "family": "Hu",
        "given": "C.C."
      }
    ],
    "publisher": "Science Press",
    "type": "book",
    "issued": "2002",
    "page": "277–309",
    "publisher-place": "Beijing"
  },
  {
    "author": [
      {
        "family": "Hu",
        "given": "J.Q."
      },
      {
        "family": "Deng",
        "given": "Y.F."
      },
      {
        "family": "Thomas",
        "given": "F.D."
      }
    ],
    "title": "Acanthaceae",
    "editor": [
      {
        "family": "Wu",
        "given": "Z.Y."
      },
      {
        "family": "Raven",
        "given": "P.H."
      },
      {
        "family": "Hong",
        "given": "D.Y."
      }
    ],
    "publisher": "Science Press",
    "type": "book",
    "issued": "2011",
    "page": "449–461",
    "publisher-place": "Beijing"
  },
  {
    "author": [
      {
        "family": "Standards",
        "given": "I.U.C.N."
      },
      {
        "family": "Subcommittee",
        "given": "Petitions"
      }
    ],
    "title": "Guidelines for using the IUCN Red List Categories and Criteria. Version 13. Prepared by the Standards and Petitions Subcommittee",
    "note": "Available from:",
    "type": null,
    "issued": "2017",
    "URL": "http://www.iucnredlist.org/documents/RedListGuidelines.pdf"
  },
  {
    "author": [
      {
        "family": "Linnaeus",
        "given": "C."
      }
    ],
    "title": "Species plantarum 1",
    "publisher": "Laurentius Salvius, Stockholm",
    "type": "book",
    "issued": "1753",
    "page": "560"
  },
  {
    "author": [
      {
        "family": "Ridley",
        "given": "H.N."
      }
    ],
    "title": "Acanthaceae",
    "editor": [
      {
        "family": "Ridley",
        "given": "H.N."
      }
    ],
    "container-title": "Flora of Malay Peninsula 2",
    "publisher": "L. Reeve & Co",
    "type": "chapter",
    "issued": "1923",
    "page": "554–610",
    "publisher-place": "London"
  },
  {
    "author": [
      {
        "family": "Smith",
        "given": "W.W."
      }
    ],
    "title": "Diagnoses specierum novarum in herbario Horti Regii Botanici Edinburgensis cognitarum (Species asiaticae",
    "volume": "10",
    "type": "article-journal",
    "container-title": "CCCLICCCC. Notes from the Royal Botanic Gardens, Edinburgh",
    "issued": "1918",
    "page": "174–175"
  },
  {
    "author": [
      {
        "family": "Smith",
        "given": "W.W."
      }
    ],
    "title": "Diagnoses specierum novarum in herbario Horti Regii Botanici Edinburgensis cognitarum, CCCCI-CCCCL",
    "volume": "11",
    "type": "article-journal",
    "container-title": "Notes from the Royal Botanic Gardens, Edinburgh",
    "issued": "1919",
    "page": "191–232"
  },
  {
    "author": [
      {
        "family": "Solms-Laubach",
        "given": "H.M.C.L.F."
      }
    ],
    "title": "Acanthaceae",
    "editor": [
      {
        "family": "Schweinfurth",
        "given": "G."
      }
    ],
    "publisher": "Druck und Verlag von Georg Reimer",
    "type": "book",
    "issued": "1867",
    "page": "102–114",
    "publisher-place": "Berlin"
  },
  {
    "author": [
      {
        "family": "Turland",
        "given": "N.J."
      },
      {
        "family": "Wiersema",
        "given": "J.H."
      },
      {
        "family": "Barrie",
        "given": "F.R."
      },
      {
        "family": "Greuter",
        "given": "W."
      },
      {
        "family": "Hawksworth",
        "given": "D.L."
      },
      {
        "family": "Herendeen",
        "given": "P.S."
      },
      {
        "family": "Knapp",
        "given": "S."
      },
      {
        "family": "Kusber",
        "given": "W.H."
      },
      {
        "family": "Li",
        "given": "D.Z."
      },
      {
        "family": "Marhold",
        "given": "K."
      },
      {
        "family": "May",
        "given": "T.W."
      },
      {
        "family": "McNeill",
        "given": "J."
      },
      {
        "family": "Monro",
        "given": "A.M."
      },
      {
        "family": "Prado",
        "given": "J."
      },
      {
        "family": "Price",
        "given": "M.J."
      },
      {
        "given": "Smith"
      }
    ],
    "title": "G.F",
    "editor": [
      {
        "literal": "Eds."
      }
    ],
    "container-title": "International Code of Nomenclature for algae, fungi, and plants (Shenzhen Code) adopted by the Nineteenth International Botanical Congress Shenzhen",
    "publisher": "Koeltz Botanical Books",
    "type": "chapter",
    "issued": "2018",
    "page": "254",
    "publisher-place": "China",
    "URL": "https://doi.org/10.12705/Code.2018",
    "DOI": "10.12705/Code.2018"
  },
  {
    "author": [
      {
        "family": "Wu",
        "given": "Z.Y."
      }
    ],
    "title": "Index Florae Yunnanensis 2",
    "publisher": "People’s Publishing Press of Yunnan",
    "type": "book",
    "issued": "1984",
    "page": "1670–1671",
    "publisher-place": "Kunming"
  }
]
