[
  {
    "author": [
      {
        "family": "Baker",
        "given": "J.B."
      }
    ],
    "title": "Rhynchosia",
    "editor": [
      {
        "family": "Hooker",
        "given": "J.D."
      },
      {
        "family": "Reeve",
        "given": "L."
      },
      {
        "given": "Co"
      }
    ],
    "container-title": "Flora of British India",
    "volume": "II",
    "publisher": "Covent Garden",
    "type": "chapter",
    "issued": "1876",
    "page": "220–226",
    "publisher-place": "Henrietta Street"
  },
  {
    "author": [
      {
        "family": "Bentham",
        "given": "G."
      }
    ],
    "title": "Commentationes de leguminosarum generibus",
    "publisher": "Sollinger",
    "type": "book",
    "issued": "1837",
    "publisher-place": "Vienna"
  },
  {
    "author": [
      {
        "family": "De Candolle",
        "given": "A."
      }
    ],
    "title": "Prodromus Systematus Naturalis. 2. Sumptibus Sociorum Treuttel et Wurtz",
    "type": null,
    "issued": "1825",
    "page": "384–389",
    "publisher-place": "Paris"
  },
  {
    "author": [
      {
        "family": "Gamble",
        "given": "J.S."
      }
    ],
    "title": "Flora of the Presidency of Madras",
    "volume": "1",
    "publisher": "Adlard & Son, limited",
    "type": "book",
    "issued": "1928",
    "page": "21,",
    "publisher-place": "Hart Street"
  },
  {
    "author": [
      {
        "family": "Grear",
        "given": "J.W."
      }
    ],
    "title": "A revision of the New World species of Rhynchosia (Leguminosae-Faboideae",
    "volume": "31",
    "type": "article-journal",
    "container-title": "Memoirs of the New York Botanical Garden",
    "issued": "1978",
    "page": "1–168"
  },
  {
    "author": [
      {
        "family": "Lewis",
        "given": "G.P."
      },
      {
        "family": "Schrire",
        "given": "B.D."
      },
      {
        "family": "Mackinder",
        "given": "B.A."
      },
      {
        "family": "Lock",
        "given": "M."
      }
    ],
    "title": "Legumes of the world",
    "type": "article-journal",
    "container-title": "The Royal Botanic Gardens, Kew",
    "issued": "2005"
  },
  {
    "author": [
      {
        "family": "Loureiro",
        "given": "J.D."
      }
    ],
    "title": "Flora Cochinchinensis",
    "volume": "2",
    "type": null,
    "issued": "1790",
    "page": "460"
  },
  {
    "author": [
      {
        "family": "Makino",
        "given": "T."
      }
    ],
    "volume": "II",
    "type": "article-journal",
    "container-title": "The Journal of Japanese Botany",
    "issue": "4",
    "issued": "1920",
    "page": "14"
  },
  {
    "author": [
      {
        "family": "Maximowicz",
        "given": "C.J."
      }
    ],
    "title": "Melanges Biologiques Tires Du Bulletin De L’Academie Imperlale Des Sciences De St",
    "volume": "IX",
    "type": "article-journal",
    "container-title": "Petersbourg",
    "issued": "1877",
    "page": "70"
  },
  {
    "author": [
      {
        "family": "Pullaiah",
        "given": "T."
      },
      {
        "family": "Sri Ramamurthy",
        "given": "K."
      }
    ],
    "title": "Flora of Eastern Ghats, hill ranges of south East India",
    "volume": "2",
    "publisher": "Leguminosae). Regency publications",
    "type": "book",
    "issued": "2000",
    "page": "300–322",
    "publisher-place": "New Delhi"
  },
  {
    "author": [
      {
        "family": "Sanjappa",
        "given": "M."
      }
    ],
    "title": "Legumes of India",
    "editor": [
      {
        "family": "Singh",
        "given": "Bishen Singh Mahendra Pal"
      },
      {
        "family": "Dun",
        "given": "Dehra"
      }
    ],
    "container-title": "India",
    "type": "chapter",
    "issued": "1992",
    "page": "236–241"
  },
  {
    "author": [
      {
        "family": "Turland",
        "given": "N.J."
      },
      {
        "family": "Wiersema",
        "given": "J.H."
      },
      {
        "family": "Barrir",
        "given": "F.R."
      },
      {
        "family": "Greuter",
        "given": "W."
      },
      {
        "family": "Hawksworth",
        "given": "D.L."
      },
      {
        "family": "Herendeen",
        "given": "P.S."
      },
      {
        "family": "Knapp",
        "given": "S."
      },
      {
        "family": "Kusber",
        "given": "W.-H."
      },
      {
        "family": "Li",
        "given": "D.-Z."
      },
      {
        "family": "Marhold",
        "given": "K."
      },
      {
        "family": "May",
        "given": "T.W."
      },
      {
        "family": "McNeill",
        "given": "J."
      },
      {
        "family": "Monro",
        "given": "A.M."
      },
      {
        "family": "Prado",
        "given": "J."
      },
      {
        "family": "Price",
        "given": "M.J."
      },
      {
        "given": "Smith"
      }
    ],
    "title": "G.F",
    "editor": [
      {
        "literal": "Eds."
      }
    ],
    "container-title": "International Code of Nomenclature for algae, fungi and plants (Shenzhen Code) adopted by the Nineteenth International Botanical Congress Shenzhen",
    "note": "Regnum Vegetabile 159].",
    "publisher": "Koeltz Botanical Books, Glashutten",
    "type": "chapter",
    "issued": "2018",
    "page": "254",
    "publisher-place": "China",
    "URL": "https://doi.org/10.12705/Code.2018",
    "DOI": "10.12705/Code.2018"
  }
]
