[
  {
    "author": [
      {
        "family": "Ansari",
        "given": "A.A."
      }
    ],
    "title": "Crotalaria L",
    "editor": [
      {
        "family": "Singh",
        "given": "India Bishen Singh Mahendra Pal"
      },
      {
        "given": "Dehradun"
      }
    ],
    "type": null,
    "issued": "2008",
    "page": "312"
  },
  {
    "author": [
      {
        "family": "Fyson",
        "given": "P.F."
      }
    ],
    "title": "The Flora of the South Indian Hill Stations: Ootacamujnd, Coonoor, Kotagiri, Kodaikanal, Yercaud, and the country round",
    "volume": "I",
    "genre": "Superintendent,",
    "publisher": "Government Press",
    "type": null,
    "issued": "1932",
    "page": "138–153",
    "publisher-place": "Madras"
  },
  {
    "author": [
      {
        "family": "Gamble",
        "given": "J.S."
      }
    ],
    "title": "Flora of the Presidency of Madras",
    "volume": "1",
    "publisher": "London",
    "type": "article-journal",
    "container-title": "repr.ed",
    "issued": "1918",
    "page": "212",
    "publisher-place": "Calcutta"
  },
  {
    "author": [
      {
        "family": "Kottaimuthu",
        "given": "R."
      },
      {
        "family": "Vasudevan",
        "given": "N."
      }
    ],
    "title": "Additions to the legumes of Sirumalai Hills, Tamil Nadu, India",
    "volume": "8",
    "type": "article-journal",
    "container-title": "Sciencia Acta Xaveriana",
    "issued": "2012",
    "page": "167–171"
  },
  {
    "author": [
      {
        "family": "Kottaimuthu",
        "given": "R."
      }
    ],
    "title": "Floristic studies on Dicots of Karandamalai, Southern Eastern Ghats, Tamil Nadu, India",
    "publisher": "Lambert Academic Publishing, Saarbrücken",
    "type": "book",
    "issued": "2014",
    "page": "520"
  },
  {
    "author": [
      {
        "family": "Kottaimuthu",
        "given": "R."
      },
      {
        "family": "Suresh",
        "given": "K."
      },
      {
        "family": "Kumuthakalavalli",
        "given": "R."
      }
    ],
    "title": "Additions to the legumes of Eastern Ghats, India",
    "volume": "11",
    "type": "article-journal",
    "container-title": "Plant Archives",
    "issued": "2011",
    "page": "447–448"
  },
  {
    "author": [
      {
        "family": "Kumar",
        "given": "S."
      },
      {
        "family": "Sane",
        "given": "P.V."
      },
      {
        "family": "Mabberley",
        "given": "D.J."
      }
    ],
    "title": "Legumes of South Asia - A checklist",
    "publisher": "Kew Publishing, Kew",
    "edition": "3rd",
    "type": "book",
    "issued": "2003",
    "page": "536"
  },
  {
    "author": [
      {
        "family": "Matthew",
        "given": "K.M."
      }
    ],
    "title": "Flora of the Tamil Nadu Carnatic, Vol.1-3. St",
    "publisher": "Joseph’s College, the Rapinat Herbarium",
    "type": "book",
    "issued": "1983",
    "page": "2152",
    "publisher-place": "Tiruchirapalli, India"
  },
  {
    "author": [
      {
        "family": "Pallithanam",
        "given": "J.P."
      }
    ],
    "title": "A Pocket Flora of the Sirumalai Hills, South India",
    "container-title": "The Rapinat Herbarium, Tiruchirapalli",
    "type": "chapter",
    "issued": "2001",
    "page": "65–68"
  },
  {
    "author": [
      {
        "family": "Parthasarathy",
        "given": "N."
      },
      {
        "family": "Karthikeyan",
        "given": "R."
      }
    ],
    "title": "Plant Biodiversity Inventory and Conservation of Two Tropical Dry Evergreen Forests on the Coromandel Coast, South India",
    "volume": "6",
    "type": "article-journal",
    "container-title": "Biodiversity and Conservation",
    "issued": "1997",
    "page": "1063–1083",
    "URL": "http://dx.doi.org/10.1023/A:1018328016810",
    "DOI": "10.1023/A:1018328016810"
  },
  {
    "author": [
      {
        "family": "Sanjappa",
        "given": "M."
      }
    ],
    "title": "Legume of India. Dehra Dun, Bishen Singh Mahendra",
    "publisher": "Survey of India, Coimbatore",
    "type": "book",
    "issued": "1992",
    "page": "128"
  },
  {
    "author": [
      {
        "family": "Udayakumar",
        "given": "M."
      },
      {
        "family": "Parthasarathy",
        "given": "N."
      }
    ],
    "title": "Angiosperms, Tropical Dry Evergreen Forests of Southern Coromandel Coast, India",
    "volume": "6",
    "type": "article-journal",
    "container-title": "Check List",
    "issue": "3",
    "issued": "2010",
    "page": "368–381"
  },
  {
    "author": [
      {
        "family": "Vajravelu",
        "given": "E."
      }
    ],
    "title": "Papilionaceae",
    "editor": [
      {
        "family": "Nair",
        "given": "N.C."
      },
      {
        "family": "Henry",
        "given": "A.N."
      }
    ],
    "container-title": "Flora of Tamil Nadu. India. Series-1: Analysis",
    "volume": "1",
    "publisher": "Botanical Survey of India, Calcutta",
    "type": "chapter",
    "issued": "1983",
    "page": "100"
  },
  {
    "author": [
      {
        "family": "Venkateswaran",
        "given": "R."
      },
      {
        "family": "Parthasarathy",
        "given": "N."
      }
    ],
    "title": "Tropical Dry Evergreen Forests on the Coromandel Coast of India: Structure, Composition and Human Disturbance",
    "volume": "9",
    "type": "article-journal",
    "container-title": "Ecotropica",
    "issue": "1–2",
    "issued": "2003",
    "page": "45–58"
  }
]
