[
  {
    "author": [
      {
        "family": "Camfield",
        "given": "R."
      },
      {
        "family": "Hughes",
        "given": "M."
      },
      {
        "given": "Begoniaceae"
      }
    ],
    "title": "A revision and one new species of Begonia L",
    "volume": "396",
    "type": "article-journal",
    "container-title": "European Journal of Taxonomy",
    "issued": "2018",
    "page": "1–116",
    "URL": "https://doi.org/10.5852/ejt.2018.396",
    "DOI": "10.5852/ejt.2018.396"
  },
  {
    "author": [
      {
        "family": "Chen",
        "given": "W.H."
      },
      {
        "family": "Radbouchoom",
        "given": "S."
      },
      {
        "family": "Nguyen",
        "given": "H.Q."
      },
      {
        "family": "Nguyen",
        "given": "H.T."
      },
      {
        "family": "Nguyen",
        "given": "K.S."
      },
      {
        "family": "Shui",
        "given": "Y.M."
      }
    ],
    "title": "Seven new species of Begonia (Begoniaceae) in northern Vietnam and southern China",
    "volume": "94",
    "type": "article-journal",
    "container-title": "PhytoKeys",
    "issued": "2018",
    "page": "65–85",
    "URL": "https://doi.org/10.3897/phytokeys.94.23248",
    "DOI": "10.3897/phytokeys.94.23248"
  },
  {
    "author": [
      {
        "family": "De Candolle",
        "given": "A."
      }
    ],
    "title": "Memorire sur la famille des Begoniaceae",
    "volume": "IV 11",
    "type": "article-journal",
    "container-title": "Annales des Science Naturelles- Botanique",
    "issued": "1859",
    "page": "92–149"
  },
  {
    "author": [
      {
        "family": "Ding",
        "given": "B."
      },
      {
        "family": "Nakamura",
        "given": "K."
      },
      {
        "family": "Kono",
        "given": "Y."
      },
      {
        "family": "Ho",
        "given": "M.J."
      },
      {
        "family": "Peng",
        "given": "C.I."
      }
    ],
    "title": "Begonia jinyunensis (Begoniaceae, section Platycentrum), a new palmately compound leaved species from Chongqing, China",
    "volume": "55",
    "type": "article-journal",
    "container-title": "Botanical Studies",
    "issued": "2014",
    "page": "62–69",
    "URL": "https://doi.org/10.1186/s40529-014-0062-6",
    "DOI": "10.1186/s40529-014-0062-6"
  },
  {
    "author": [
      {
        "family": "Doorenbos",
        "given": "J."
      },
      {
        "family": "Sosef",
        "given": "M.S.M."
      },
      {
        "family": "Wilde",
        "given": "J.J.F.E.",
        "particle": "de"
      }
    ],
    "title": "The sections of Begonia including descriptions, keys, and species lists (Studies in Begoniaceae VI",
    "volume": "98",
    "type": "article-journal",
    "container-title": "Wageningen Agricultural University Papers",
    "issued": "1998",
    "page": "1–266"
  },
  {
    "author": [
      {
        "family": "Dunn",
        "given": "S.T."
      }
    ],
    "title": "Decades Kewensis: Plantarum Novarum in Herbario Horti Regii Conservatarum. Decas XCVI",
    "volume": "3",
    "type": "article-journal",
    "container-title": "Bulletin of Miscellaneous Information",
    "issued": "1920",
    "page": "108–111"
  },
  {
    "author": [
      {
        "family": "Geddes",
        "given": "E.T."
      }
    ],
    "title": "Contributions to the Flora of Siam",
    "volume": "6",
    "type": "article-journal",
    "container-title": "Additamentum XXV. Bulletin of Miscellaneous Information, Kew",
    "issued": "1928",
    "page": "234–247"
  },
  {
    "author": [
      {
        "literal": "Gu, C.Z., Peng, C.I &Turland, N.J."
      }
    ],
    "title": "Begoniaceae",
    "editor": [
      {
        "family": "Wu",
        "given": "C.Y."
      },
      {
        "family": "Raven",
        "given": "P.H."
      }
    ],
    "publisher": "Science Press",
    "type": "book",
    "issued": "2007",
    "page": "153–207",
    "publisher-place": "Beijing"
  },
  {
    "author": [
      {
        "family": "Hara",
        "given": "H."
      }
    ],
    "title": "New or noteworthy flowering plants from Eastern Himalaya (8",
    "volume": "45",
    "type": "article-journal",
    "container-title": "Journal of Japanese Botany",
    "issued": "1970",
    "page": "91–92"
  },
  {
    "author": [
      {
        "family": "Hemsley",
        "given": "W.B."
      }
    ],
    "title": "Begonia cathayana",
    "volume": "134",
    "type": "article-journal",
    "container-title": "Curtis’s Botanical Magazine",
    "issued": "1908",
    "page": "8202"
  },
  {
    "author": [
      {
        "family": "Hooker",
        "given": "J.D."
      }
    ],
    "title": "Begonia xanthina",
    "volume": "78",
    "type": "article-journal",
    "container-title": "Curtis’s Botanical Magazine",
    "issued": "1852",
    "page": "4683"
  },
  {
    "author": [
      {
        "family": "Hughes",
        "given": "M."
      },
      {
        "family": "Moonlight",
        "given": "P."
      },
      {
        "family": "Jara",
        "given": "A."
      },
      {
        "family": "Tebbitt",
        "given": "M."
      },
      {
        "family": "Wilson",
        "given": "H."
      },
      {
        "family": "Pullan",
        "given": "M."
      }
    ],
    "title": "Begonia Resource Centre",
    "note": "Available from:",
    "type": null,
    "issued": "2015",
    "URL": "http://padme.rbge.org.uk/begonia/"
  },
  {
    "author": [
      {
        "family": "Irmscher",
        "given": "E."
      }
    ],
    "title": "Die Begoniaceen Chinas und ihre Bedeutung fur die Frage der Formbildung in polymorphen Sippen",
    "volume": "10",
    "type": "article-journal",
    "container-title": "Mitteilungen aus dem Institut für allgemeine Botanik in Hamburg",
    "issued": "1939",
    "page": "431–557"
  },
  {
    "author": [
      {
        "given": "I.U.C.N."
      }
    ],
    "title": "Guidelines for Using the IUCN Red List Categories and Criteria. Version 13. Prepared by the Standards and Petitions Sub-Committee",
    "note": "Available from:",
    "type": null,
    "issued": "2017",
    "URL": "http://www.iucnredlist.org/documents/RedListGuidelines.pdf"
  },
  {
    "author": [
      {
        "family": "Klotzsch",
        "given": "J.F."
      }
    ],
    "title": "Begoniaceen-Gattungen und Arten",
    "container-title": "Abhandlungen der Königlichen Akademie der Wissenschaften zu",
    "type": "chapter",
    "issued": "1855",
    "page": "121– 255",
    "publisher-place": "Berlin"
  },
  {
    "author": [
      {
        "family": "Ku",
        "given": "S.M."
      },
      {
        "family": "Kono",
        "given": "Y."
      },
      {
        "family": "Liu",
        "given": "Y."
      }
    ],
    "title": "Begonia pengii (sect. Coelocentrum, Begoniaceae), a new species from limestone areas in Guangxi, China",
    "volume": "49",
    "type": "article-journal",
    "container-title": "Botanical Studies",
    "issued": "2008",
    "page": "167–175"
  },
  {
    "author": [
      {
        "family": "Li",
        "given": "C."
      },
      {
        "family": "Yang",
        "given": "L.H."
      },
      {
        "family": "Tian",
        "given": "D.K."
      },
      {
        "family": "Chen",
        "given": "Y."
      },
      {
        "family": "Wu",
        "given": "R.J."
      },
      {
        "family": "Fu",
        "given": "N.F."
      }
    ],
    "title": "Begonia leipingensis (Begoniaceae), a new compound-leaved species with unique petiolule pattern from Guangxi of China",
    "volume": "244",
    "type": "article-journal",
    "container-title": "Phytotaxa",
    "issue": "1",
    "issued": "2016",
    "page": "45–56",
    "URL": "https://doi.org/10.11646/phytotaxa.244.1.3",
    "DOI": "10.11646/phytotaxa.244.1.3"
  },
  {
    "author": [
      {
        "family": "Li",
        "given": "H.Z."
      },
      {
        "family": "Guan",
        "given": "K.Y."
      },
      {
        "family": "Lin",
        "given": "C.W."
      },
      {
        "family": "Peng",
        "given": "C.I."
      }
    ],
    "title": "Begonia qingchengshanensis (sect. Reichenheimia, Begoniaceae), a new species from Sichuan, China",
    "volume": "349",
    "type": "article-journal",
    "container-title": "Phytotaxa",
    "issue": "2",
    "issued": "2018",
    "page": "197–200",
    "URL": "https://doi.org/10.11646/phytotaxa.349.2.12",
    "DOI": "10.11646/phytotaxa.349.2.12"
  },
  {
    "author": [
      {
        "family": "Li",
        "given": "H.Z."
      },
      {
        "family": "Ma",
        "given": "H."
      },
      {
        "family": "Zhou",
        "given": "Z.K."
      },
      {
        "family": "Guan",
        "given": "K.Y."
      }
    ],
    "title": "A new species of Begonia (Begoniaceae) from Guangxi, China",
    "volume": "157",
    "type": "article-journal",
    "container-title": "Botanical Journal of the Linnean Society",
    "issued": "2008",
    "page": "83–90",
    "URL": "https://doi.org/10.1111/j.1095-8339.2008.00771.x",
    "DOI": "10.1111/j.1095-8339.2008.00771.x"
  },
  {
    "author": [
      {
        "family": "Linneaus",
        "given": "C."
      }
    ],
    "title": "Species plantarum, exhibentes plantas rite cognitas ad genera relatas, cum differentiis specificis, nominibus trivialibus, synonymis selectis, locis natalibus, secundum systema sexuale digestas",
    "type": "article-journal",
    "container-title": "Imprensis Laurentii Salvii, Homiae",
    "issued": "1753",
    "page": null
  },
  {
    "author": [
      {
        "family": "Liu",
        "given": "Y."
      },
      {
        "family": "Ku",
        "given": "S.M."
      },
      {
        "family": "Peng",
        "given": "C.I."
      }
    ],
    "title": "Begonia bamaensis (sect. Coelocentrum, Begoniaceae), a new species from limestone areas in Guangxi, China",
    "volume": "48",
    "type": "article-journal",
    "container-title": "Botanical Studies",
    "issued": "2007",
    "page": "465–473"
  },
  {
    "author": [
      {
        "family": "Ma",
        "given": "H."
      },
      {
        "family": "Li",
        "given": "H.Z."
      }
    ],
    "title": "Begonia guaniana (Begoniaceae), a new species from China",
    "volume": "43",
    "type": "article-journal",
    "container-title": "Annales Botanici Fennici",
    "issued": "2006",
    "page": "466–477"
  },
  {
    "author": [
      {
        "family": "Moonlight",
        "given": "P.W."
      },
      {
        "family": "Ardi",
        "given": "W.H."
      },
      {
        "family": "Padilla",
        "given": "L.A."
      },
      {
        "family": "Chung",
        "given": "K.F."
      },
      {
        "family": "Fuller",
        "given": "D."
      },
      {
        "family": "Girmansyah",
        "given": "D."
      },
      {
        "family": "Hollands",
        "given": "R."
      },
      {
        "family": "Jara-Munoz",
        "given": "A."
      },
      {
        "family": "Kiew",
        "given": "R."
      },
      {
        "family": "Leong",
        "given": "W.C."
      },
      {
        "family": "Liu",
        "given": "Y."
      },
      {
        "family": "Mahardika",
        "given": "A."
      },
      {
        "family": "Marasinghe",
        "given": "L.D.K."
      },
      {
        "family": "O’Connor",
        "given": "M."
      },
      {
        "family": "Peng",
        "given": "C.I."
      },
      {
        "family": "Perez",
        "given": "A.J."
      },
      {
        "family": "Phutthai",
        "given": "T."
      },
      {
        "family": "Pullan",
        "given": "M."
      },
      {
        "family": "Rajbhandary",
        "given": "S."
      },
      {
        "family": "Reynel",
        "given": "C."
      },
      {
        "family": "Rubite",
        "given": "R.R."
      },
      {
        "family": "Sang",
        "given": "J."
      },
      {
        "family": "Scherberich",
        "given": "D."
      },
      {
        "family": "Shui",
        "given": "Y.M."
      },
      {
        "family": "Tebbitt",
        "given": "M.C."
      },
      {
        "family": "Thomas",
        "given": "D.C."
      },
      {
        "family": "Wilson",
        "given": "H.P."
      },
      {
        "family": "Zaini",
        "given": "N.H."
      },
      {
        "family": "Hughes",
        "given": "M."
      }
    ],
    "title": "Dividing and conquering the fastest-growing genus: Towards a natural sectional classification of the mega-diverse genus Begonia (Begoniaceae",
    "volume": "67",
    "type": "article-journal",
    "container-title": "Taxon",
    "issue": "2",
    "issued": "2018",
    "page": "267–323",
    "URL": "https://doi.org/10.12705/672.3",
    "DOI": "10.12705/672.3"
  },
  {
    "author": [
      {
        "family": "Peng",
        "given": "C.I."
      },
      {
        "family": "Jin",
        "given": "X.H."
      },
      {
        "family": "Ku",
        "given": "S.M."
      },
      {
        "family": "Kono",
        "given": "K."
      },
      {
        "family": "Huang",
        "given": "H.Y."
      },
      {
        "family": "Yang",
        "given": "H.A."
      }
    ],
    "title": "Begonia wuzhishanensis (sect. Diploclinium, Begoniaceae), a new species from Hainan Island, China",
    "volume": "55",
    "type": "article-journal",
    "container-title": "Botanical Studies",
    "issued": "2014",
    "page": "24–30",
    "URL": "https://doi.org/10.1186/1999-3110-55-24",
    "DOI": "10.1186/1999-3110-55-24"
  },
  {
    "author": [
      {
        "family": "Peng",
        "given": "C.I."
      },
      {
        "family": "Ku",
        "given": "S.M."
      },
      {
        "family": "Kono",
        "given": "Y."
      },
      {
        "family": "Liu",
        "given": "Y."
      }
    ],
    "title": "Begonia chongzuoensis (sect. Coelocentrum, Begoniaceae), a new calciphilefrom Guangxi, China",
    "volume": "53",
    "type": "article-journal",
    "container-title": "Botanical Studies",
    "issued": "2012",
    "page": "283–290"
  },
  {
    "author": [
      {
        "family": "Peng",
        "given": "C.I."
      },
      {
        "family": "Ku",
        "given": "S.M."
      },
      {
        "family": "Yang",
        "given": "H.A."
      },
      {
        "family": "Leong",
        "given": "W.C."
      },
      {
        "family": "Liu",
        "given": "Y."
      },
      {
        "family": "Nguyen",
        "given": "T.H."
      },
      {
        "family": "Kono",
        "given": "Y."
      },
      {
        "family": "Chung",
        "given": "K.F."
      }
    ],
    "title": "Two new species of Begonia sect",
    "editor": [
      {
        "family": "Coelocentrum",
        "given": "B.guixiensis"
      },
      {
        "given": "B."
      }
    ],
    "volume": "55",
    "type": "article-journal",
    "container-title": "Botanical Studies",
    "issued": "2014",
    "page": "52–63",
    "URL": "https://doi.org/10.1186/s40529-014-0052-8",
    "DOI": "10.1186/s40529-014-0052-8"
  },
  {
    "author": [
      {
        "family": "Peng",
        "given": "C.I."
      },
      {
        "family": "Yang",
        "given": "H.A."
      },
      {
        "family": "Kono",
        "given": "Y."
      },
      {
        "family": "Chung",
        "given": "K.F."
      },
      {
        "family": "Huang",
        "given": "Y.S."
      },
      {
        "family": "Wu",
        "given": "W.H."
      },
      {
        "family": "Liu",
        "given": "Y."
      }
    ],
    "title": "Novelties in Begonia sect",
    "editor": [
      {
        "family": "Coelocentrum",
        "given": "B.longgangensis"
      },
      {
        "given": "B."
      }
    ],
    "volume": "54",
    "type": "article-journal",
    "container-title": "Botanical Studies",
    "issued": "2013",
    "page": "1–9",
    "URL": "https://doi.org/10.1186/1999-3110-54-44",
    "DOI": "10.1186/1999-3110-54-44"
  },
  {
    "author": [
      {
        "family": "Peng",
        "given": "C.I."
      },
      {
        "family": "Ku",
        "given": "S.M."
      },
      {
        "family": "Kono",
        "given": "Y."
      },
      {
        "family": "Chung",
        "given": "K.F."
      },
      {
        "family": "Liu",
        "given": "Y."
      }
    ],
    "title": "Two new species of Begonia (sect. Coelocentrum,Begoniaceae) from limestone areas in Guangxi, China: B",
    "volume": "49",
    "type": "article-journal",
    "container-title": "arachnoidea and B. subcoriacea. Botanical Studies",
    "issued": "2008",
    "page": "405–418"
  },
  {
    "author": [
      {
        "family": "Peng",
        "given": "C.I."
      },
      {
        "family": "Liu",
        "given": "Y."
      },
      {
        "family": "Kono",
        "given": "Y."
      }
    ],
    "title": "Begonia ×breviscapa (Begoniaceae), a new intersectional natural hybrid from limestone areas in Guangxi, China",
    "volume": "51",
    "type": "article-journal",
    "container-title": "Botanical Studies",
    "issued": "2010",
    "page": "107–117"
  },
  {
    "author": [
      {
        "family": "Peng",
        "given": "C.I."
      },
      {
        "family": "Liu",
        "given": "Y."
      },
      {
        "family": "Ku",
        "given": "S.M."
      }
    ],
    "title": "Begonia aurantiflora (sect. Coelocentrum, Begoniaceae), a new species from limestone areas in Guangxi, China",
    "volume": "49",
    "type": "article-journal",
    "container-title": "Botanical Studies",
    "issued": "2008",
    "page": "83–92"
  },
  {
    "author": [
      {
        "family": "Peng",
        "given": "C.I."
      },
      {
        "family": "Ku",
        "given": "S.M."
      }
    ],
    "title": "Begonia ×chungii (Begoniaceae), a new natural hybrid in Taiwan",
    "volume": "50",
    "type": "article-journal",
    "container-title": "Botanical Studies",
    "issued": "2009",
    "page": "241–250"
  },
  {
    "author": [
      {
        "family": "Qin",
        "given": "Y.H."
      },
      {
        "family": "Liang",
        "given": "Y.Y."
      },
      {
        "family": "Xu",
        "given": "W.B."
      },
      {
        "family": "Lin",
        "given": "C.W."
      },
      {
        "family": "Peng",
        "given": "C.I."
      }
    ],
    "title": "Begonia ufoides (sect. coelocentrum, Begoniaceae), a new species from limestone areas in central Guangxi, China",
    "volume": "316",
    "type": "article-journal",
    "container-title": "Phytotaxa",
    "issue": "3",
    "issued": "2017",
    "page": "279–284",
    "URL": "https://doi.org/10.11646/phytotaxa.316.3.7",
    "DOI": "10.11646/phytotaxa.316.3.7"
  },
  {
    "author": [
      {
        "family": "Shui",
        "given": "Y.M."
      },
      {
        "family": "Huang",
        "given": "S.H."
      }
    ],
    "title": "Notes on the Genus Begonia from Yunnan",
    "volume": "21",
    "type": "article-journal",
    "container-title": "Acta Botanica Yunnanica",
    "issue": "1",
    "issued": "1999",
    "page": "11–23"
  },
  {
    "author": [
      {
        "family": "Shui",
        "given": "Y.M."
      }
    ],
    "title": "Begonia tetralobata (Begoniaceae), a new species from China",
    "volume": "44",
    "type": "article-journal",
    "container-title": "Annales Botanici Fennici",
    "issued": "2007",
    "page": "76–79"
  },
  {
    "author": [
      {
        "family": "Tian",
        "given": "D.K."
      },
      {
        "family": "Li",
        "given": "C."
      },
      {
        "family": "Li",
        "given": "C.H."
      },
      {
        "family": "Li",
        "given": "X.J."
      }
    ],
    "title": "Begonia pulchrifolia (sect. platycentrum), a new species of Begoniaceae from Sichuan of China",
    "volume": "207",
    "type": "article-journal",
    "container-title": "Phytotaxa",
    "issue": "3",
    "issued": "2015",
    "page": "242–252",
    "URL": "https://doi.org/10.11646/phytotaxa.207.3.2",
    "DOI": "10.11646/phytotaxa.207.3.2"
  },
  {
    "author": [
      {
        "family": "Wei",
        "given": "Z.D."
      },
      {
        "family": "Shui",
        "given": "Y.M."
      },
      {
        "family": "Zhang",
        "given": "M.D."
      },
      {
        "family": "Zhang",
        "given": "R.M."
      },
      {
        "family": "Shui",
        "given": "M."
      },
      {
        "given": "Z."
      }
    ],
    "title": "Begonia coelocentroides Y",
    "volume": "45",
    "type": "article-journal",
    "container-title": "Acta Phytotaxonomica Sinica",
    "issued": "2007",
    "page": "86–89"
  },
  {
    "author": [
      {
        "family": "Wu",
        "given": "C.Y."
      },
      {
        "family": "Ku",
        "given": "T.C."
      }
    ],
    "title": "New taxa of Begonia from China (cont",
    "volume": "35",
    "type": "article-journal",
    "container-title": "Acta Phytotaxonomica Sinica",
    "issue": "1",
    "issued": "1997",
    "page": "34–56"
  }
]
